LICENSE.rst
MANIFEST.in
README.md
pyproject.toml
setup.py
movel/__init__.py
movel/moment.py
movel.egg-info/PKG-INFO
movel.egg-info/SOURCES.txt
movel.egg-info/dependency_links.txt
movel.egg-info/requires.txt
movel.egg-info/top_level.txt