Metadata-Version: 2.1
Name: movel
Version: 0.1
Summary: calculating the moment of velocity
Author-email: Kaitlyn Chen <kaichen@g.hmc.edu>
License: BSD 3-Clause License
Project-URL: homepage, https://github.com/kaitlynchen1/moment-of-velocity/tree/main
License-File: LICENSE.rst
Requires-Dist: numpy
Requires-Dist: pandas
Requires-Dist: matplotlib
